[{"nombre": "uvas", "imagen_url": "https://lingokids.com/wp-content/uploads/2020/11/20172F092F152F132F162F142Fee0f7af7-92f9-4037-b0c3-41513145ff952FGrapes.png", "pronunciaci\u00f3n": "/\u02c8u\u03b2as/", "italiano": {"nombre": "uva", "pronunciaci\u00f3n": "/\u02c8uva/"}, "ingles": {"nombre": "grapes", "pronunciaci\u00f3n": "/\u0261re\u026aps/"}}, {"nombre": "lima", "imagen_url": "https://lingokids.com/wp-content/uploads/2020/11/20172F092F152F132F162F142F1976a7af-0290-4630-99b0-25bf1044173d2FLime.png", "pronunciaci\u00f3n": "/\u02c8lima/", "italiano": {"nombre": "lime", "pronunciaci\u00f3n": "/\u02c8lime/"}, "ingles": {"nombre": "lime", "pronunciaci\u00f3n": "/la\u026am/"}}, {"nombre": "lim\u00f3n", "imagen_url": "https://lingokids.com/wp-content/uploads/2020/11/20172F092F152F132F162F142Fae01d711-60fb-41e0-9c7a-aa2126e930a12FLemon.png", "pronunciaci\u00f3n": "/li\u02c8mon/", "italiano": {"nombre": "limone", "pronunciaci\u00f3n": "/li\u02c8mo.ne/"}, "ingles": {"nombre": "lemon", "pronunciaci\u00f3n": "/\u02c8l\u025bm\u0259n/"}}, {"nombre": "cereza", "imagen_url": "https://lingokids.com/wp-content/uploads/2020/11/20172F092F152F132F162F142F6bd367ab-4d0d-4da6-a48d-99f0228c58112FCherries.png", "pronunciaci\u00f3n": "/se\u02c8\u027eesa/", "italiano": {"nombre": "ciliegia", "pronunciaci\u00f3n": "/t\u0283i\u02c8lj\u025bd\u0292a/"}, "ingles": {"nombre": "cherry", "pronunciaci\u00f3n": "/\u02c8t\u0283\u025bri/"}}, {"nombre": "ar\u00e1ndano", "imagen_url": "https://lingokids.com/wp-content/uploads/2020/11/20172F092F152F132F162F142F19f5c846-9bcd-4f7d-bbe5-fa75b4233f3a2FBlueberry.png", "pronunciaci\u00f3n": "/a\u02c8\u027eandano/", "italiano": {"nombre": "mirtillo", "pronunciaci\u00f3n": "/mir\u02c8til.lo/"}, "ingles": {"nombre": "blueberry", "pronunciaci\u00f3n": "/\u02c8blu\u02d0\u02ccb\u025bri/"}}, {"nombre": "banana", "imagen_url": "https://lingokids.com/wp-content/uploads/2020/11/20172F092F152F132F162F142Fa8b54aa7-ed88-4df7-8bf7-b3c22d2c57f32FBanana.png", "pronunciaci\u00f3n": "/ba\u02c8nana/", "italiano": {"nombre": "banana", "pronunciaci\u00f3n": "/ba\u02c8na.na/"}, "ingles": {"nombre": "banana", "pronunciaci\u00f3n": "/b\u0259\u02c8n\u00e6n\u0259/"}}, {"nombre": "manzana", "imagen_url": "https://lingokids.com/wp-content/uploads/2020/11/20172F092F152F132F162F142Fa77dbe0b-8cc2-48bb-b8c8-ef2944878e332FApple.png", "pronunciaci\u00f3n": "/man\u02c8\u03b8ana/", "italiano": {"nombre": "mela", "pronunciaci\u00f3n": "/\u02c8me.la/"}, "ingles": {"nombre": "apple", "pronunciaci\u00f3n": "/\u02c8\u00e6p\u0259l/"}}, {"nombre": "sand\u00eda", "imagen_url": "https://lingokids.com/wp-content/uploads/2020/11/20172F092F152F132F162F152Ff0f095ec-7514-47df-8795-26ba5e153c862FWatermelon.png", "pronunciaci\u00f3n": "/san\u02c8di.a/", "italiano": {"nombre": "anguria", "pronunciaci\u00f3n": "/an\u02c8\u0261u.rja/"}, "ingles": {"nombre": "watermelon", "pronunciaci\u00f3n": "/\u02c8w\u0254\u02d0t\u0259r\u02ccm\u025bl\u0259n/"}}, {"nombre": "durazno", "imagen_url": "https://lingokids.com/wp-content/uploads/2020/11/20172F092F152F132F162F152F231a4254-7849-42cd-8c7b-bc6d979b738b2FPeach.png", "pronunciaci\u00f3n": "/du\u02c8\u027easno/", "italiano": {"nombre": "pesca", "pronunciaci\u00f3n": "/\u02c8pes.ka/"}, "ingles": {"nombre": "peach", "pronunciaci\u00f3n": "/pi\u02d0t\u0283/"}}, {"nombre": "anan\u00e1", "imagen_url": "https://lingokids.com/wp-content/uploads/2020/11/20172F092F152F132F162F152F2303d0c1-0df9-48a8-a2ab-39b27fd14ca32FPineapple.png", "pronunciaci\u00f3n": "/ana\u02c8na/", "italiano": {"nombre": "ananas", "pronunciaci\u00f3n": "/\u02c8a.na.nas/"}, "ingles": {"nombre": "pineapple", "pronunciaci\u00f3n": "/\u02c8pa\u026an\u02cc\u00e6p\u0259l/"}}, {"nombre": "frutilla", "imagen_url": "https://lingokids.com/wp-content/uploads/2020/11/20172F092F152F132F162F152Fd0ccc4bb-d13b-4bfc-9376-0eb115bf13002FStrawberry.png", "pronunciaci\u00f3n": "/f\u027eu\u02c8ti\u029da/", "italiano": {"nombre": "fragola", "pronunciaci\u00f3n": "/\u02c8fra.\u0261o.la/"}, "ingles": {"nombre": "strawberry", "pronunciaci\u00f3n": "/\u02c8str\u0254\u02d0\u02ccb\u025bri/"}}, {"nombre": "naranja", "imagen_url": "https://lingokids.com/wp-content/uploads/2020/11/20172F092F152F132F162F152Fb96f77f1-2d17-4c9b-987a-cbcf754640a12FOrangeFruit.png", "pronunciaci\u00f3n": "/na\u02c8\u027ea\u014bxa/", "italiano": {"nombre": "arancia", "pronunciaci\u00f3n": "/a\u02c8rant\u0283a/"}, "ingles": {"nombre": "orange", "pronunciaci\u00f3n": "/\u02c8\u0254\u02d0r\u026and\u0292/"}}]